{
	"generatedAt": "2026-06-01T18:20:45.302Z",
	"legacy2022": {
		"table": "81959NED",
		"title": "Verdachten; geslacht, leeftijd, migratieachtergrond en generatie 1999-2022",
		"period": {
			"key": "2022JJ00",
			"year": 2022,
			"title": "2022",
			"status": "Voorlopig",
			"description": "Voorlopige cijfers"
		},
		"selection": {
			"geslacht": "Totaal mannen en vrouwen",
			"leeftijd": "Totaal",
			"generatie": "Totaal"
		},
		"quartiles": {
			"q1": 65,
			"median": 103,
			"q3": 180
		},
		"points": [
			{
				"key": "T001040",
				"label": "Totaal",
				"group": 1,
				"isAggregate": true,
				"totalSuspects": 158290,
				"suspectsWithDutchAddress": 130310,
				"suspectsPer10000": 83,
				"populationEstimate": 15700000,
				"year": 2022,
				"source": "81959NED"
			},
			{
				"key": "2012605",
				"label": "Met migratieachtergrond",
				"group": 1,
				"isAggregate": true,
				"totalSuspects": 84520,
				"suspectsWithDutchAddress": 59520,
				"suspectsPer10000": 150,
				"populationEstimate": 3968000,
				"year": 2022,
				"source": "81959NED"
			},
			{
				"key": "1012600",
				"label": "Nederlandse achtergrond",
				"group": 1,
				"isAggregate": true,
				"totalSuspects": 72890,
				"suspectsWithDutchAddress": 70790,
				"suspectsPer10000": 61,
				"populationEstimate": 11604918,
				"year": 2022,
				"source": "81959NED"
			},
			{
				"key": "2012657",
				"label": "Niet-westerse migratieachtergrond",
				"group": 1,
				"isAggregate": true,
				"totalSuspects": 52840,
				"suspectsWithDutchAddress": 44140,
				"suspectsPer10000": 202,
				"populationEstimate": 2185149,
				"year": 2022,
				"source": "81959NED"
			},
			{
				"key": "2012655",
				"label": "Westerse migratieachtergrond",
				"group": 1,
				"isAggregate": true,
				"totalSuspects": 31680,
				"suspectsWithDutchAddress": 15380,
				"suspectsPer10000": 86,
				"populationEstimate": 1788372,
				"year": 2022,
				"source": "81959NED"
			},
			{
				"key": "H008673",
				"label": "Marokko",
				"group": 3,
				"isAggregate": false,
				"totalSuspects": 12810,
				"suspectsWithDutchAddress": 10470,
				"suspectsPer10000": 295,
				"populationEstimate": 354915,
				"year": 2022,
				"source": "81959NED"
			},
			{
				"key": "H008718",
				"label": "Polen",
				"group": 6,
				"isAggregate": false,
				"totalSuspects": 8340,
				"suspectsWithDutchAddress": 3180,
				"suspectsPer10000": 165,
				"populationEstimate": 192727,
				"year": 2022,
				"source": "81959NED"
			},
			{
				"key": "H008751",
				"label": "Suriname",
				"group": 4,
				"isAggregate": false,
				"totalSuspects": 7950,
				"suspectsWithDutchAddress": 7530,
				"suspectsPer10000": 227,
				"populationEstimate": 331718,
				"year": 2022,
				"source": "81959NED"
			},
			{
				"key": "H008766",
				"label": "Turkije",
				"group": 6,
				"isAggregate": false,
				"totalSuspects": 6600,
				"suspectsWithDutchAddress": 6160,
				"suspectsPer10000": 161,
				"populationEstimate": 382609,
				"year": 2022,
				"source": "81959NED"
			},
			{
				"key": "H007119",
				"label": "(voormalige) Nederlandse Antillen, Aruba",
				"group": 4,
				"isAggregate": false,
				"totalSuspects": 5650,
				"suspectsWithDutchAddress": 5250,
				"suspectsPer10000": 357,
				"populationEstimate": 147059,
				"year": 2022,
				"source": "81959NED"
			},
			{
				"key": "1012950",
				"label": "Overige migratieachtergrond",
				"group": 8,
				"isAggregate": true,
				"totalSuspects": 3770,
				"suspectsWithDutchAddress": 2750,
				"suspectsPer10000": 169,
				"populationEstimate": 162722,
				"year": 2022,
				"source": "81959NED"
			},
			{
				"key": "H007172",
				"label": "Voormalige Sovjet-Unie",
				"group": 6,
				"isAggregate": false,
				"totalSuspects": 3480,
				"suspectsWithDutchAddress": 1500,
				"suspectsPer10000": 95,
				"populationEstimate": 157895,
				"year": 2022,
				"source": "81959NED"
			},
			{
				"key": "H008723",
				"label": "Roemenië",
				"group": 6,
				"isAggregate": false,
				"totalSuspects": 3420,
				"suspectsWithDutchAddress": 550,
				"suspectsPer10000": 121,
				"populationEstimate": 45455,
				"year": 2022,
				"source": "81959NED"
			},
			{
				"key": "H008592",
				"label": "Duitsland",
				"group": 6,
				"isAggregate": false,
				"totalSuspects": 2650,
				"suspectsWithDutchAddress": 1740,
				"suspectsPer10000": 55,
				"populationEstimate": 316364,
				"year": 2022,
				"source": "81959NED"
			},
			{
				"key": "H008753",
				"label": "Syrië",
				"group": 5,
				"isAggregate": false,
				"totalSuspects": 2380,
				"suspectsWithDutchAddress": 2010,
				"suspectsPer10000": 191,
				"populationEstimate": 105236,
				"year": 2022,
				"source": "81959NED"
			},
			{
				"key": "H008535",
				"label": "Algerije",
				"group": 3,
				"isAggregate": false,
				"totalSuspects": 2360,
				"suspectsWithDutchAddress": 230,
				"suspectsPer10000": 273,
				"populationEstimate": 8425,
				"year": 2022,
				"source": "81959NED"
			},
			{
				"key": "H008552",
				"label": "België",
				"group": 6,
				"isAggregate": false,
				"totalSuspects": 1780,
				"suspectsWithDutchAddress": 830,
				"suspectsPer10000": 77,
				"populationEstimate": 107792,
				"year": 2022,
				"source": "81959NED"
			},
			{
				"key": "H008632",
				"label": "Indonesië",
				"group": 5,
				"isAggregate": false,
				"totalSuspects": 1660,
				"suspectsWithDutchAddress": 1600,
				"suspectsPer10000": 47,
				"populationEstimate": 340426,
				"year": 2022,
				"source": "81959NED"
			},
			{
				"key": "H008567",
				"label": "Bulgarije",
				"group": 6,
				"isAggregate": false,
				"totalSuspects": 1550,
				"suspectsWithDutchAddress": 800,
				"suspectsPer10000": 175,
				"populationEstimate": 45714,
				"year": 2022,
				"source": "81959NED"
			},
			{
				"key": "H007069",
				"label": "(voormalig) Joegoslavië",
				"group": 6,
				"isAggregate": false,
				"totalSuspects": 1390,
				"suspectsWithDutchAddress": 1040,
				"suspectsPer10000": 137,
				"populationEstimate": 75912,
				"year": 2022,
				"source": "81959NED"
			},
			{
				"key": "H008633",
				"label": "Irak",
				"group": 5,
				"isAggregate": false,
				"totalSuspects": 1260,
				"suspectsWithDutchAddress": 1110,
				"suspectsPer10000": 196,
				"populationEstimate": 56633,
				"year": 2022,
				"source": "81959NED"
			},
			{
				"key": "H008747",
				"label": "Somalië",
				"group": 3,
				"isAggregate": false,
				"totalSuspects": 1260,
				"suspectsWithDutchAddress": 1080,
				"suspectsPer10000": 344,
				"populationEstimate": 31395,
				"year": 2022,
				"source": "81959NED"
			},
			{
				"key": "H008605",
				"label": "Frankrijk",
				"group": 6,
				"isAggregate": false,
				"totalSuspects": 1170,
				"suspectsWithDutchAddress": 330,
				"suspectsPer10000": 73,
				"populationEstimate": 45205,
				"year": 2022,
				"source": "81959NED"
			},
			{
				"key": "H008749",
				"label": "Spanje",
				"group": 6,
				"isAggregate": false,
				"totalSuspects": 1000,
				"suspectsWithDutchAddress": 490,
				"suspectsPer10000": 102,
				"populationEstimate": 48039,
				"year": 2022,
				"source": "81959NED"
			},
			{
				"key": "H008776",
				"label": "Verenigd Koninkrijk",
				"group": 6,
				"isAggregate": false,
				"totalSuspects": 840,
				"suspectsWithDutchAddress": 640,
				"suspectsPer10000": 74,
				"populationEstimate": 86486,
				"year": 2022,
				"source": "81959NED"
			},
			{
				"key": "H008533",
				"label": "Afghanistan",
				"group": 5,
				"isAggregate": false,
				"totalSuspects": 800,
				"suspectsWithDutchAddress": 730,
				"suspectsPer10000": 159,
				"populationEstimate": 45912,
				"year": 2022,
				"source": "81959NED"
			},
			{
				"key": "H008634",
				"label": "Iran",
				"group": 5,
				"isAggregate": false,
				"totalSuspects": 800,
				"suspectsWithDutchAddress": 710,
				"suspectsPer10000": 154,
				"populationEstimate": 46104,
				"year": 2022,
				"source": "81959NED"
			},
			{
				"key": "H008636",
				"label": "Italië",
				"group": 6,
				"isAggregate": false,
				"totalSuspects": 720,
				"suspectsWithDutchAddress": 500,
				"suspectsPer10000": 84,
				"populationEstimate": 59524,
				"year": 2022,
				"source": "81959NED"
			},
			{
				"key": "H008719",
				"label": "Portugal",
				"group": 6,
				"isAggregate": false,
				"totalSuspects": 620,
				"suspectsWithDutchAddress": 380,
				"suspectsPer10000": 134,
				"populationEstimate": 28358,
				"year": 2022,
				"source": "81959NED"
			},
			{
				"key": "H008765",
				"label": "Tunesië",
				"group": 3,
				"isAggregate": false,
				"totalSuspects": 620,
				"suspectsWithDutchAddress": 270,
				"suspectsPer10000": 272,
				"populationEstimate": 9926,
				"year": 2022,
				"source": "81959NED"
			},
			{
				"key": "H008644",
				"label": "Kaapverdië",
				"group": 3,
				"isAggregate": false,
				"totalSuspects": 570,
				"suspectsWithDutchAddress": 530,
				"suspectsPer10000": 249,
				"populationEstimate": 21285,
				"year": 2022,
				"source": "81959NED"
			},
			{
				"key": "H007204",
				"label": "Voormalig Tsjecho-Slowakije",
				"group": 6,
				"isAggregate": false,
				"totalSuspects": 530,
				"suspectsWithDutchAddress": 220,
				"suspectsPer10000": 110,
				"populationEstimate": 20000,
				"year": 2022,
				"source": "81959NED"
			},
			{
				"key": "H008594",
				"label": "Egypte",
				"group": 3,
				"isAggregate": false,
				"totalSuspects": 520,
				"suspectsWithDutchAddress": 470,
				"suspectsPer10000": 181,
				"populationEstimate": 25967,
				"year": 2022,
				"source": "81959NED"
			},
			{
				"key": "H008627",
				"label": "Hongarije",
				"group": 6,
				"isAggregate": false,
				"totalSuspects": 510,
				"suspectsWithDutchAddress": 220,
				"suspectsPer10000": 88,
				"populationEstimate": 25000,
				"year": 2022,
				"source": "81959NED"
			},
			{
				"key": "H008579",
				"label": "Colombia",
				"group": 4,
				"isAggregate": false,
				"totalSuspects": 480,
				"suspectsWithDutchAddress": 320,
				"suspectsPer10000": 180,
				"populationEstimate": 17778,
				"year": 2022,
				"source": "81959NED"
			},
			{
				"key": "H008591",
				"label": "Dominicaanse Republiek",
				"group": 4,
				"isAggregate": false,
				"totalSuspects": 480,
				"suspectsWithDutchAddress": 450,
				"suspectsPer10000": 320,
				"populationEstimate": 14063,
				"year": 2022,
				"source": "81959NED"
			},
			{
				"key": "H008562",
				"label": "Brazilië",
				"group": 4,
				"isAggregate": false,
				"totalSuspects": 450,
				"suspectsWithDutchAddress": 340,
				"suspectsPer10000": 106,
				"populationEstimate": 32075,
				"year": 2022,
				"source": "81959NED"
			},
			{
				"key": "H008612",
				"label": "Ghana",
				"group": 3,
				"isAggregate": false,
				"totalSuspects": 450,
				"suspectsWithDutchAddress": 410,
				"suspectsPer10000": 178,
				"populationEstimate": 23034,
				"year": 2022,
				"source": "81959NED"
			},
			{
				"key": "H008699",
				"label": "Nigeria",
				"group": 3,
				"isAggregate": false,
				"totalSuspects": 390,
				"suspectsWithDutchAddress": 270,
				"suspectsPer10000": 187,
				"populationEstimate": 14439,
				"year": 2022,
				"source": "81959NED"
			},
			{
				"key": "H008575",
				"label": "China",
				"group": 5,
				"isAggregate": false,
				"totalSuspects": 380,
				"suspectsWithDutchAddress": 340,
				"suspectsPer10000": 46,
				"populationEstimate": 73913,
				"year": 2022,
				"source": "81959NED"
			},
			{
				"key": "H008599",
				"label": "Ethiopië",
				"group": 3,
				"isAggregate": false,
				"totalSuspects": 380,
				"suspectsWithDutchAddress": 360,
				"suspectsPer10000": 159,
				"populationEstimate": 22642,
				"year": 2022,
				"source": "81959NED"
			},
			{
				"key": "H008710",
				"label": "Pakistan",
				"group": 5,
				"isAggregate": false,
				"totalSuspects": 330,
				"suspectsWithDutchAddress": 290,
				"suspectsPer10000": 123,
				"populationEstimate": 23577,
				"year": 2022,
				"source": "81959NED"
			},
			{
				"key": "H008778",
				"label": "Verenigde Staten van Amerika",
				"group": 4,
				"isAggregate": false,
				"totalSuspects": 330,
				"suspectsWithDutchAddress": 250,
				"suspectsPer10000": 59,
				"populationEstimate": 42373,
				"year": 2022,
				"source": "81959NED"
			},
			{
				"key": "H008539",
				"label": "Angola",
				"group": 3,
				"isAggregate": false,
				"totalSuspects": 300,
				"suspectsWithDutchAddress": 270,
				"suspectsPer10000": 354,
				"populationEstimate": 7627,
				"year": 2022,
				"source": "81959NED"
			},
			{
				"key": "H008631",
				"label": "India",
				"group": 5,
				"isAggregate": false,
				"totalSuspects": 300,
				"suspectsWithDutchAddress": 260,
				"suspectsPer10000": 45,
				"populationEstimate": 57778,
				"year": 2022,
				"source": "81959NED"
			},
			{
				"key": "H008582",
				"label": "Congo (Democratische Republiek)",
				"group": 3,
				"isAggregate": false,
				"totalSuspects": 240,
				"suspectsWithDutchAddress": 200,
				"suspectsPer10000": 274,
				"populationEstimate": 7299,
				"year": 2022,
				"source": "81959NED"
			},
			{
				"key": "H008787",
				"label": "Zuid-Afrika",
				"group": 3,
				"isAggregate": false,
				"totalSuspects": 200,
				"suspectsWithDutchAddress": 180,
				"suspectsPer10000": 64,
				"populationEstimate": 28125,
				"year": 2022,
				"source": "81959NED"
			},
			{
				"key": "H008746",
				"label": "Soedan",
				"group": 3,
				"isAggregate": false,
				"totalSuspects": 190,
				"suspectsWithDutchAddress": 150,
				"suspectsPer10000": 209,
				"populationEstimate": 7177,
				"year": 2022,
				"source": "81959NED"
			},
			{
				"key": "H008739",
				"label": "Sierra Leone",
				"group": 3,
				"isAggregate": false,
				"totalSuspects": 180,
				"suspectsWithDutchAddress": 160,
				"suspectsPer10000": 320,
				"populationEstimate": 5000,
				"year": 2022,
				"source": "81959NED"
			},
			{
				"key": "H008545",
				"label": "Australië",
				"group": 7,
				"isAggregate": false,
				"totalSuspects": 170,
				"suspectsWithDutchAddress": 150,
				"suspectsPer10000": 96,
				"populationEstimate": 15625,
				"year": 2022,
				"source": "81959NED"
			},
			{
				"key": "H008757",
				"label": "Thailand",
				"group": 5,
				"isAggregate": false,
				"totalSuspects": 170,
				"suspectsWithDutchAddress": 170,
				"suspectsPer10000": 83,
				"populationEstimate": 20482,
				"year": 2022,
				"source": "81959NED"
			},
			{
				"key": "H008780",
				"label": "Vietnam",
				"group": 5,
				"isAggregate": false,
				"totalSuspects": 170,
				"suspectsWithDutchAddress": 150,
				"suspectsPer10000": 69,
				"populationEstimate": 21739,
				"year": 2022,
				"source": "81959NED"
			},
			{
				"key": "H008629",
				"label": "Ierland",
				"group": 6,
				"isAggregate": false,
				"totalSuspects": 150,
				"suspectsWithDutchAddress": 80,
				"suspectsPer10000": 72,
				"populationEstimate": 11111,
				"year": 2022,
				"source": "81959NED"
			},
			{
				"key": "H008658",
				"label": "Libanon",
				"group": 5,
				"isAggregate": false,
				"totalSuspects": 140,
				"suspectsWithDutchAddress": 130,
				"suspectsPer10000": 178,
				"populationEstimate": 7303,
				"year": 2022,
				"source": "81959NED"
			},
			{
				"key": "H008574",
				"label": "Chili",
				"group": 4,
				"isAggregate": false,
				"totalSuspects": 130,
				"suspectsWithDutchAddress": 80,
				"suspectsPer10000": 129,
				"populationEstimate": 6202,
				"year": 2022,
				"source": "81959NED"
			},
			{
				"key": "H008603",
				"label": "Filippijnen",
				"group": 5,
				"isAggregate": false,
				"totalSuspects": 130,
				"suspectsWithDutchAddress": 120,
				"suspectsPer10000": 52,
				"populationEstimate": 23077,
				"year": 2022,
				"source": "81959NED"
			},
			{
				"key": "H008750",
				"label": "Sri Lanka",
				"group": 5,
				"isAggregate": false,
				"totalSuspects": 130,
				"suspectsWithDutchAddress": 110,
				"suspectsPer10000": 104,
				"populationEstimate": 10577,
				"year": 2022,
				"source": "81959NED"
			},
			{
				"key": "H008571",
				"label": "Canada",
				"group": 4,
				"isAggregate": false,
				"totalSuspects": 120,
				"suspectsWithDutchAddress": 110,
				"suspectsPer10000": 71,
				"populationEstimate": 15493,
				"year": 2022,
				"source": "81959NED"
			},
			{
				"key": "H008774",
				"label": "Venezuela",
				"group": 4,
				"isAggregate": false,
				"totalSuspects": 120,
				"suspectsWithDutchAddress": 100,
				"suspectsPer10000": 115,
				"populationEstimate": 8696,
				"year": 2022,
				"source": "81959NED"
			},
			{
				"key": "H008709",
				"label": "Oostenrijk",
				"group": 6,
				"isAggregate": false,
				"totalSuspects": 110,
				"suspectsWithDutchAddress": 70,
				"suspectsPer10000": 49,
				"populationEstimate": 14286,
				"year": 2022,
				"source": "81959NED"
			},
			{
				"key": "H008716",
				"label": "Peru",
				"group": 4,
				"isAggregate": false,
				"totalSuspects": 110,
				"suspectsWithDutchAddress": 60,
				"suspectsPer10000": 80,
				"populationEstimate": 7500,
				"year": 2022,
				"source": "81959NED"
			},
			{
				"key": "H008635",
				"label": "Israël",
				"group": 5,
				"isAggregate": false,
				"totalSuspects": 100,
				"suspectsWithDutchAddress": 70,
				"suspectsPer10000": 83,
				"populationEstimate": 8434,
				"year": 2022,
				"source": "81959NED"
			},
			{
				"key": "H008623",
				"label": "Guyana",
				"group": 4,
				"isAggregate": false,
				"totalSuspects": 90,
				"suspectsWithDutchAddress": 80,
				"suspectsPer10000": 199,
				"populationEstimate": 4020,
				"year": 2022,
				"source": "81959NED"
			},
			{
				"key": "H008542",
				"label": "Argentinië",
				"group": 4,
				"isAggregate": false,
				"totalSuspects": 80,
				"suspectsWithDutchAddress": 60,
				"suspectsPer10000": 78,
				"populationEstimate": 7692,
				"year": 2022,
				"source": "81959NED"
			},
			{
				"key": "H008791",
				"label": "Zwitserland",
				"group": 6,
				"isAggregate": false,
				"totalSuspects": 80,
				"suspectsWithDutchAddress": 70,
				"suspectsPer10000": 60,
				"populationEstimate": 11667,
				"year": 2022,
				"source": "81959NED"
			},
			{
				"key": "H008790",
				"label": "Zweden",
				"group": 6,
				"isAggregate": false,
				"totalSuspects": 70,
				"suspectsWithDutchAddress": 40,
				"suspectsPer10000": 54,
				"populationEstimate": 7407,
				"year": 2022,
				"source": "81959NED"
			},
			{
				"key": "H008628",
				"label": "Hongkong",
				"group": 5,
				"isAggregate": false,
				"totalSuspects": 60,
				"suspectsWithDutchAddress": 60,
				"suspectsPer10000": 32,
				"populationEstimate": 18750,
				"year": 2022,
				"source": "81959NED"
			},
			{
				"key": "H008697",
				"label": "Nieuw-Zeeland",
				"group": 7,
				"isAggregate": false,
				"totalSuspects": 60,
				"suspectsWithDutchAddress": 50,
				"suspectsPer10000": 94,
				"populationEstimate": 5319,
				"year": 2022,
				"source": "81959NED"
			},
			{
				"key": "H008789",
				"label": "Zuid-Korea",
				"group": 5,
				"isAggregate": false,
				"totalSuspects": 60,
				"suspectsWithDutchAddress": 50,
				"suspectsPer10000": 69,
				"populationEstimate": 7246,
				"year": 2022,
				"source": "81959NED"
			},
			{
				"key": "H008680",
				"label": "Mexico",
				"group": 4,
				"isAggregate": false,
				"totalSuspects": 50,
				"suspectsWithDutchAddress": 30,
				"suspectsPer10000": 39,
				"populationEstimate": 7692,
				"year": 2022,
				"source": "81959NED"
			},
			{
				"key": "H008588",
				"label": "Denemarken",
				"group": 6,
				"isAggregate": false,
				"totalSuspects": 40,
				"suspectsWithDutchAddress": 40,
				"suspectsPer10000": 56,
				"populationEstimate": 7143,
				"year": 2022,
				"source": "81959NED"
			},
			{
				"key": "H008669",
				"label": "Maleisië",
				"group": 5,
				"isAggregate": false,
				"totalSuspects": 40,
				"suspectsWithDutchAddress": 30,
				"suspectsPer10000": 53,
				"populationEstimate": 5660,
				"year": 2022,
				"source": "81959NED"
			},
			{
				"key": "H008604",
				"label": "Finland",
				"group": 6,
				"isAggregate": false,
				"totalSuspects": 30,
				"suspectsWithDutchAddress": 30,
				"suspectsPer10000": 54,
				"populationEstimate": 5556,
				"year": 2022,
				"source": "81959NED"
			},
			{
				"key": "H008704",
				"label": "Noorwegen",
				"group": 6,
				"isAggregate": false,
				"totalSuspects": 30,
				"suspectsWithDutchAddress": 20,
				"suspectsPer10000": 51,
				"populationEstimate": 3922,
				"year": 2022,
				"source": "81959NED"
			},
			{
				"key": "H008740",
				"label": "Singapore",
				"group": 5,
				"isAggregate": false,
				"totalSuspects": 30,
				"suspectsWithDutchAddress": 30,
				"suspectsPer10000": 53,
				"populationEstimate": 5660,
				"year": 2022,
				"source": "81959NED"
			},
			{
				"key": "H008639",
				"label": "Japan",
				"group": 5,
				"isAggregate": false,
				"totalSuspects": 20,
				"suspectsWithDutchAddress": 20,
				"suspectsPer10000": 19,
				"populationEstimate": 10526,
				"year": 2022,
				"source": "81959NED"
			}
		]
	},
	"currentSeries": {
		"table": "85658NED",
		"title": "Verdachten; geslacht, leeftijd, herkomst, opleiding, huishoudensinkomen",
		"selection": {
			"geslacht": "Totaal mannen en vrouwen",
			"leeftijd": "Totaal",
			"geboorteland": "Totaal",
			"opleiding": "Totaal opleidingen",
			"huishoudensinkomen": "Totaal"
		},
		"periods": [
			{
				"key": "2022JJ00",
				"year": 2022,
				"title": "2022",
				"status": "Definitief",
				"description": ""
			},
			{
				"key": "2023JJ00",
				"year": 2023,
				"title": "2023",
				"status": "Definitief",
				"description": "Voorlopige cijfers"
			},
			{
				"key": "2024JJ00",
				"year": 2024,
				"title": "2024",
				"status": "Voorlopig",
				"description": "Provisional figures Voorlopige cijfers"
			},
			{
				"key": "2025JJ00",
				"year": 2025,
				"title": "2025",
				"status": "Voorlopig",
				"description": "Provisional figures"
			}
		],
		"series": [
			{
				"key": "T001040",
				"label": "Totaal",
				"group": 5,
				"year": 2022,
				"status": "Definitief",
				"statusDescription": "",
				"totalSuspects": 155650,
				"suspectsPer10000": 84,
				"source": "85658NED"
			},
			{
				"key": "1012600",
				"label": "Nederland",
				"group": 6,
				"year": 2022,
				"status": "Definitief",
				"statusDescription": "",
				"totalSuspects": 72980,
				"suspectsPer10000": 62,
				"source": "85658NED"
			},
			{
				"key": "H007933",
				"label": "Europa (exclusief Nederland)",
				"group": 5,
				"year": 2022,
				"status": "Definitief",
				"statusDescription": "",
				"totalSuspects": 26790,
				"suspectsPer10000": 94,
				"source": "85658NED"
			},
			{
				"key": "2820717",
				"label": "Buiten Europa (excl. 5 grote herkomst...",
				"group": 5,
				"year": 2022,
				"status": "Definitief",
				"statusDescription": "",
				"totalSuspects": 20540,
				"suspectsPer10000": 142,
				"source": "85658NED"
			},
			{
				"key": "H008673",
				"label": "Marokko",
				"group": 7,
				"year": 2022,
				"status": "Definitief",
				"statusDescription": "",
				"totalSuspects": 12350,
				"suspectsPer10000": 301,
				"source": "85658NED"
			},
			{
				"key": "H008751",
				"label": "Suriname",
				"group": 7,
				"year": 2022,
				"status": "Definitief",
				"statusDescription": "",
				"totalSuspects": 8060,
				"suspectsPer10000": 228,
				"source": "85658NED"
			},
			{
				"key": "H008766",
				"label": "Turkije",
				"group": 7,
				"year": 2022,
				"status": "Definitief",
				"statusDescription": "",
				"totalSuspects": 6670,
				"suspectsPer10000": 161,
				"source": "85658NED"
			},
			{
				"key": "H007119",
				"label": "Nederlandse Cariben",
				"group": 7,
				"year": 2022,
				"status": "Definitief",
				"statusDescription": "",
				"totalSuspects": 5880,
				"suspectsPer10000": 340,
				"source": "85658NED"
			},
			{
				"key": "H008632",
				"label": "Indonesië",
				"group": 7,
				"year": 2022,
				"status": "Definitief",
				"statusDescription": "",
				"totalSuspects": 1730,
				"suspectsPer10000": 47,
				"source": "85658NED"
			},
			{
				"key": "T001040",
				"label": "Totaal",
				"group": 5,
				"year": 2023,
				"status": "Definitief",
				"statusDescription": "Voorlopige cijfers",
				"totalSuspects": 148800,
				"suspectsPer10000": 79,
				"source": "85658NED"
			},
			{
				"key": "1012600",
				"label": "Nederland",
				"group": 6,
				"year": 2023,
				"status": "Definitief",
				"statusDescription": "Voorlopige cijfers",
				"totalSuspects": 66790,
				"suspectsPer10000": 56,
				"source": "85658NED"
			},
			{
				"key": "H007933",
				"label": "Europa (exclusief Nederland)",
				"group": 5,
				"year": 2023,
				"status": "Definitief",
				"statusDescription": "Voorlopige cijfers",
				"totalSuspects": 27670,
				"suspectsPer10000": 92,
				"source": "85658NED"
			},
			{
				"key": "2820717",
				"label": "Buiten Europa (excl. 5 grote herkomst...",
				"group": 5,
				"year": 2023,
				"status": "Definitief",
				"statusDescription": "Voorlopige cijfers",
				"totalSuspects": 21070,
				"suspectsPer10000": 132,
				"source": "85658NED"
			},
			{
				"key": "H008673",
				"label": "Marokko",
				"group": 7,
				"year": 2023,
				"status": "Definitief",
				"statusDescription": "Voorlopige cijfers",
				"totalSuspects": 11520,
				"suspectsPer10000": 277,
				"source": "85658NED"
			},
			{
				"key": "H008751",
				"label": "Suriname",
				"group": 7,
				"year": 2023,
				"status": "Definitief",
				"statusDescription": "Voorlopige cijfers",
				"totalSuspects": 7510,
				"suspectsPer10000": 210,
				"source": "85658NED"
			},
			{
				"key": "H008766",
				"label": "Turkije",
				"group": 7,
				"year": 2023,
				"status": "Definitief",
				"statusDescription": "Voorlopige cijfers",
				"totalSuspects": 6360,
				"suspectsPer10000": 147,
				"source": "85658NED"
			},
			{
				"key": "H007119",
				"label": "Nederlandse Cariben",
				"group": 7,
				"year": 2023,
				"status": "Definitief",
				"statusDescription": "Voorlopige cijfers",
				"totalSuspects": 5640,
				"suspectsPer10000": 317,
				"source": "85658NED"
			},
			{
				"key": "H008632",
				"label": "Indonesië",
				"group": 7,
				"year": 2023,
				"status": "Definitief",
				"statusDescription": "Voorlopige cijfers",
				"totalSuspects": 1590,
				"suspectsPer10000": 44,
				"source": "85658NED"
			},
			{
				"key": "T001040",
				"label": "Totaal",
				"group": 5,
				"year": 2024,
				"status": "Voorlopig",
				"statusDescription": "Provisional figures Voorlopige cijfers",
				"totalSuspects": 140240,
				"suspectsPer10000": 74,
				"source": "85658NED"
			},
			{
				"key": "1012600",
				"label": "Nederland",
				"group": 6,
				"year": 2024,
				"status": "Voorlopig",
				"statusDescription": "Provisional figures Voorlopige cijfers",
				"totalSuspects": 60740,
				"suspectsPer10000": 51,
				"source": "85658NED"
			},
			{
				"key": "H007933",
				"label": "Europa (exclusief Nederland)",
				"group": 5,
				"year": 2024,
				"status": "Voorlopig",
				"statusDescription": "Provisional figures Voorlopige cijfers",
				"totalSuspects": 26360,
				"suspectsPer10000": 86,
				"source": "85658NED"
			},
			{
				"key": "2820717",
				"label": "Buiten Europa (excl. 5 grote herkomst...",
				"group": 5,
				"year": 2024,
				"status": "Voorlopig",
				"statusDescription": "Provisional figures Voorlopige cijfers",
				"totalSuspects": 20760,
				"suspectsPer10000": 126,
				"source": "85658NED"
			},
			{
				"key": "H008673",
				"label": "Marokko",
				"group": 7,
				"year": 2024,
				"status": "Voorlopig",
				"statusDescription": "Provisional figures Voorlopige cijfers",
				"totalSuspects": 11220,
				"suspectsPer10000": 270,
				"source": "85658NED"
			},
			{
				"key": "H008751",
				"label": "Suriname",
				"group": 7,
				"year": 2024,
				"status": "Voorlopig",
				"statusDescription": "Provisional figures Voorlopige cijfers",
				"totalSuspects": 7240,
				"suspectsPer10000": 200,
				"source": "85658NED"
			},
			{
				"key": "H008766",
				"label": "Turkije",
				"group": 7,
				"year": 2024,
				"status": "Voorlopig",
				"statusDescription": "Provisional figures Voorlopige cijfers",
				"totalSuspects": 6400,
				"suspectsPer10000": 145,
				"source": "85658NED"
			},
			{
				"key": "H007119",
				"label": "Nederlandse Cariben",
				"group": 7,
				"year": 2024,
				"status": "Voorlopig",
				"statusDescription": "Provisional figures Voorlopige cijfers",
				"totalSuspects": 5520,
				"suspectsPer10000": 304,
				"source": "85658NED"
			},
			{
				"key": "H008632",
				"label": "Indonesië",
				"group": 7,
				"year": 2024,
				"status": "Voorlopig",
				"statusDescription": "Provisional figures Voorlopige cijfers",
				"totalSuspects": 1350,
				"suspectsPer10000": 37,
				"source": "85658NED"
			},
			{
				"key": "T001040",
				"label": "Totaal",
				"group": 5,
				"year": 2025,
				"status": "Voorlopig",
				"statusDescription": "Provisional figures",
				"totalSuspects": 139960,
				"suspectsPer10000": 73,
				"source": "85658NED"
			},
			{
				"key": "1012600",
				"label": "Nederland",
				"group": 6,
				"year": 2025,
				"status": "Voorlopig",
				"statusDescription": "Provisional figures",
				"totalSuspects": 59460,
				"suspectsPer10000": 50,
				"source": "85658NED"
			},
			{
				"key": "H007933",
				"label": "Europa (exclusief Nederland)",
				"group": 5,
				"year": 2025,
				"status": "Voorlopig",
				"statusDescription": "Provisional figures",
				"totalSuspects": 26520,
				"suspectsPer10000": 84,
				"source": "85658NED"
			},
			{
				"key": "2820717",
				"label": "Buiten Europa (excl. 5 grote herkomst...",
				"group": 5,
				"year": 2025,
				"status": "Voorlopig",
				"statusDescription": "Provisional figures",
				"totalSuspects": 21380,
				"suspectsPer10000": 128,
				"source": "85658NED"
			},
			{
				"key": "H008673",
				"label": "Marokko",
				"group": 7,
				"year": 2025,
				"status": "Voorlopig",
				"statusDescription": "Provisional figures",
				"totalSuspects": 11180,
				"suspectsPer10000": 265,
				"source": "85658NED"
			},
			{
				"key": "H008751",
				"label": "Suriname",
				"group": 7,
				"year": 2025,
				"status": "Voorlopig",
				"statusDescription": "Provisional figures",
				"totalSuspects": 6970,
				"suspectsPer10000": 192,
				"source": "85658NED"
			},
			{
				"key": "H008766",
				"label": "Turkije",
				"group": 7,
				"year": 2025,
				"status": "Voorlopig",
				"statusDescription": "Provisional figures",
				"totalSuspects": 6360,
				"suspectsPer10000": 140,
				"source": "85658NED"
			},
			{
				"key": "H007119",
				"label": "Nederlandse Cariben",
				"group": 7,
				"year": 2025,
				"status": "Voorlopig",
				"statusDescription": "Provisional figures",
				"totalSuspects": 5580,
				"suspectsPer10000": 306,
				"source": "85658NED"
			},
			{
				"key": "H008632",
				"label": "Indonesië",
				"group": 7,
				"year": 2025,
				"status": "Voorlopig",
				"statusDescription": "Provisional figures",
				"totalSuspects": 1270,
				"suspectsPer10000": 35,
				"source": "85658NED"
			}
		]
	},
	"notes": [
		"Dit bestand bevat CBS-cijfers over geregistreerde verdachten van misdrijven, niet veroordeelden.",
		"81959NED gebruikt de oude migratieachtergrondindeling en heeft de volledige landenlijst voor 2022.",
		"85658NED gebruikt de nieuwe herkomstindeling en loopt tot 2025, maar bevat minder gedetailleerde herkomstpunten."
	]
}
